{
    "subscribers": [
        {
            "id": "1504978999",
            "expiry_date": "2024-12-31"
        },
        {
            "id": "5916936734",
            "expiry_date": "2025-01-01"
        },
        {
            "id": "-1002162553154",
            "expiry_date": "2025-01-01"
        },
        {
            "id": "7313789488",
            "expiry_date": "2027-04-23"
        },
        {
            "id": "6412134798",
            "expiry_date": "2024-08-08"
        },
        {
            "id": "5774737009",
            "expiry_date": "2024-08-08"
        },
        {
            "id": "6305897205",
            "expiry_date": "2027-04-30"
        },
        {
            "id": "5643042263",
            "expiry_date": "2026-06-01"
        },
        {
            "id": "-1002179100879",
            "expiry_date": "2027-05-03"
        }
    ]
}